unittest_expander.py
unittest_expander-0.4.4.dist-info/LICENSE.txt
unittest_expander-0.4.4.dist-info/METADATA
unittest_expander-0.4.4.dist-info/WHEEL
unittest_expander-0.4.4.dist-info/top_level.txt
unittest_expander-0.4.4.dist-info/RECORD
