Metadata-Version: 2.1
Name: unittest-expander
Version: 0.4.4
Summary: Easy and flexible unit test parametrization
Home-page: https://github.com/zuo/unittest_expander
Author: Jan Kaliszewski (zuo) and others...
Maintainer: Jan Kaliszewski (zuo)
Maintainer-email: zuo@kaliszewski.net
License: MIT
Download-URL: https://pypi.org/project/unittest_expander/#files
Project-URL: Source, https://github.com/zuo/unittest_expander
Project-URL: Documentation, https://unittest-expander.readthedocs.io/en/stable/
Project-URL: Tracker, https://github.com/zuo/unittest_expander/issues
Keywords: unittest,testing,parametrization,parameterization
Platform: UNKNOWN
Classifier: Development Status :: 4 - Beta
Classifier: Intended Audience :: Developers
Classifier: License :: OSI Approved :: MIT License
Classifier: Operating System :: OS Independent
Classifier: Programming Language :: Python
Classifier: Programming Language :: Python :: 2.7
Classifier: Programming Language :: Python :: 3
Classifier: Programming Language :: Python :: 3.6
Classifier: Programming Language :: Python :: 3.7
Classifier: Programming Language :: Python :: 3.8
Classifier: Programming Language :: Python :: 3.9
Classifier: Programming Language :: Python :: 3.10
Classifier: Programming Language :: Python :: 3.11
Classifier: Topic :: Software Development :: Testing
Requires-Python: !=3.0.*,!=3.1.*,!=3.2.*,!=3.3.*,!=3.4.*,!=3.5.*,>=2.7
